trajax_visualizer/__init__.py
trajax_visualizer/api/__init__.py
trajax_visualizer/api/config.py
trajax_visualizer/api/factory.py
trajax_visualizer/api/mpcc.py
trajax_visualizer/api/simulation.py
trajax_visualizer/assets/__init__.py
trajax_visualizer/tests/test_api.py
trajax_visualizer/assets/cli.js
trajax_visualizer-0.1.14.dist-info/METADATA
trajax_visualizer-0.1.14.dist-info/WHEEL
trajax_visualizer-0.1.14.dist-info/RECORD
