Metadata-Version: 2.4
Name: trajax-visualizer
Version: 0.1.14
Summary: Interactive visualization tool for trajax trajectory planning simulations
Author-email: Zurab Mujirishvili <zurab.mujirishvili@fau.de>
Keywords: robotics,simulation,trajectory planning,visualization
Classifier: Development Status :: 3 - Alpha
Classifier: Intended Audience :: Science/Research
Classifier: License :: OSI Approved :: MIT License
Classifier: Programming Language :: Python :: 3
Classifier: Programming Language :: Python :: 3.13
Classifier: Topic :: Scientific/Engineering :: Visualization
Classifier: Typing :: Typed
Requires-Python: >=3.13
Requires-Dist: aiofiles>=25.1.0
Requires-Dist: aiopath>=0.7.7
Requires-Dist: msgspec>=0.20.0
Requires-Dist: numpy>=2.0.0
Requires-Dist: numtypes>=0.5.1
Requires-Dist: trajax
